torchquad/__init__.py
torchquad/integration/__init__.py
torchquad/integration/base_integrator.py
torchquad/integration/boole.py
torchquad/integration/gaussian.py
torchquad/integration/grid_integrator.py
torchquad/integration/integration_grid.py
torchquad/integration/monte_carlo.py
torchquad/integration/newton_cotes.py
torchquad/integration/rng.py
torchquad/integration/simpson.py
torchquad/integration/trapezoid.py
torchquad/integration/utils.py
torchquad/integration/vegas.py
torchquad/integration/vegas_map.py
torchquad/integration/vegas_stratification.py
torchquad/utils/__init__.py
torchquad/utils/deployment_test.py
torchquad/utils/enable_cuda.py
torchquad/utils/set_log_level.py
torchquad/utils/set_precision.py
torchquad/utils/set_up_backend.py
torchquad-0.5.0.dist-info/licenses/LICENSE
torchquad-0.5.0.dist-info/METADATA
torchquad-0.5.0.dist-info/WHEEL
torchquad-0.5.0.dist-info/top_level.txt
torchquad-0.5.0.dist-info/RECORD
