Metadata-Version: 2.4
Name: torchquad
Version: 0.5.0
Summary: Package providing numerical integration methods for PyTorch, jax, TensorFlow and numpy.
Author-email: ESA Advanced Concepts Team <pablo.gomez@esa.int>
License: GPL-3.0
Project-URL: Homepage, https://github.com/esa/torchquad
Project-URL: Source, https://github.com/esa/torchquad/
Classifier: Development Status :: 3 - Alpha
Classifier: Intended Audience :: Developers
Classifier: Intended Audience :: Science/Research
Classifier: Topic :: Scientific/Engineering :: Mathematics
Classifier: License :: OSI Approved :: GNU General Public License v3 (GPLv3)
Classifier: Programming Language :: Python :: 3.8
Requires-Python: <4,>=3.8
License-File: LICENSE
Requires-Dist: loguru>=0.5.3
Requires-Dist: matplotlib>=3.3.3
Requires-Dist: scipy>=1.6.0
Requires-Dist: tqdm>=4.56.1
Requires-Dist: autoray>=0.5.0
Dynamic: license-file
